Workbook

Sheet PARÁMETROS
B1: PARÁMETROS DEL PROYECTO
B2: 535.2.2 – MEJORA CARRETERA GUADALMAR – POU 2026
B4: PARÁMETRO | C4: VALOR | D4: NOTAS
B5: Nombre del proyecto | C5: MEJORA CARRETERA GUADALMAR, MÁLAGA | D5: Nombre completo
B6: Número de expediente | C6: 535.2.2 | D6: Referencia POU 2026
B7: Promotor | C7: Ayuntamiento de Málaga
B8: Redactor del proyecto | C8: JL Antunez Ruiz Rico
B9: Plazo total de ejecución (meses) | C9: 18 | D9: ⚠ EDITABLE — controla el Gantt
B10: Fecha prevista de inicio | C10: A definir tras licitación | D10: Mes 1 del cronograma
B11: Plazo de garantía (meses) | C11: 24 | D11: Desde recepción provisional
B12: Jornadas no laborables / año | C12: 20 | D12: Por meteorología adversa (base: lluvia Málaga)
B15: LEYENDA DE COLORES
B16: Texto en azul | C16: Valor editable — input de usuario
B17: Texto en negro | C17: Fórmula calculada automáticamente
B18: Fondo azul claro | C18: Resultado / salida del modelo

Sheet PLAN DE OBRA
A1: TABLA DE ACTIVIDADES — PLAN DE OBRA
A2: =PARÁMETROS!C5
A3: ⚠ Modifica las columnas INICIO PLAN y DURACIÓN PLAN (azul). El resto se calcula automáticamente.
A5: Nº | B5: CATEGORÍA | C5: ACTIVIDAD | D5: INICIO PLAN (mes) | E5: DURACIÓN PLAN (meses) | F5: FIN PLAN (mes) | G5: % COMPL. (en ejecución)
A6: OBRA CIVIL
A7: 1 | B7: OBRA CIVIL | C7: Demoliciones | D7: 1 | E7: 2 | F7: =D7+E7-1 | G7: 0
A8: 2 | B8: OBRA CIVIL | C8: Movimiento de tierras | D8: 1 | E8: 8 | F8: =D8+E8-1 | G8: 0
A9: 3 | B9: OBRA CIVIL | C9: Muro de contención | D9: 3 | E9: 4 | F9: =D9+E9-1 | G9: 0
A10: 4 | B10: OBRA CIVIL | C10: Firmes y pavimentos | D10: 9 | E10: 7 | F10: =D10+E10-1 | G10: 0
A11: SANEAMIENTO
A12: 5 | B12: SANEAMIENTO | C12: Red saneamiento aguas pluviales | D12: 4 | E12: 8 | F12: =D12+E12-1 | G12: 0
A13: 6 | B13: SANEAMIENTO | C13: Red saneamiento aguas fecales | D13: 6 | E13: 7 | F13: =D13+E13-1 | G13: 0
A14: ABASTECIMIENTO
A15: 7 | B15: ABASTECIMIENTO | C15: Red de agua potable | D15: 10 | E15: 5 | F15: =D15+E15-1 | G15: 0
A16: ELECTRICIDAD
A17: 8 | B17: ELECTRICIDAD | C17: Red de media tensión | D17: 12 | E17: 6 | F17: =D17+E17-1 | G17: 0
A18: 9 | B18: ELECTRICIDAD | C18: Red de baja tensión | D18: 13 | E18: 3 | F18: =D18+E18-1 | G18: 0
A19: 10 | B19: ELECTRICIDAD | C19: Red de alumbrado público | D19: 15 | E19: 3 | F19: =D19+E19-1 | G19: 0
A20: TELECOMUNICACIONES
A21: 11 | B21: TELECOMUNICACIONES | C21: Red de telecomunicaciones | D21: 13 | E21: 5 | F21: =D21+E21-1 | G21: 0
A22: GAS
A23: 12 | B23: GAS | C23: Red de gas natural | D23: 13 | E23: 3 | F23: =D23+E23-1 | G23: 0
A24: URBANIZACIÓN
A25: 13 | B25: URBANIZACIÓN | C25: Red de riego | D25: 12 | E25: 3 | F25: =D25+E25-1 | G25: 0
A26: 14 | B26: URBANIZACIÓN | C26: Jardinería | D26: 12 | E26: 7 | F26: =D26+E26-1 | G26: 0
A27: 15 | B27: URBANIZACIÓN | C27: Mobiliario urbano | D27: 13 | E27: 5 | F27: =D27+E27-1 | G27: 0
A28: 16 | B28: URBANIZACIÓN | C28: Residuos sólidos urbanos (RSU) | D28: 15 | E28: 1 | F28: =D28+E28-1 | G28: 0
A29: 17 | B29: URBANIZACIÓN | C29: Señalización horizontal y vertical | D29: 16 | E29: 2 | F29: =D29+E29-1 | G29: 0
A30: CONTROL/GESTIÓN
A31: 18 | B31: CONTROL/GESTIÓN | C31: Control de calidad | D31: 1 | E31: 18 | F31: =D31+E31-1 | G31: 0
A32: 19 | B32: CONTROL/GESTIÓN | C32: Legalización y recepción de obras | D32: 12 | E32: 7 | F32: =D32+E32-1 | G32: 0
A34: PLAZO TOTAL DEL PROYECTO (según PARÁMETROS) | D34: =PARÁMETROS!C9 | E34: =PARÁMETROS!C9 | F34: =MAX(F6:F33)

Sheet GANTT
A1: DIAGRAMA DE GANTT — PLAN DE OBRA
A2: =PARÁMETROS!C5
A3: Plazo de ejecución activo: | F3: =PARÁMETROS!C9 | G3: meses
F4: OBRA CIVIL | J4: SANEAMIENTO | N4: ABASTECIMIENTO | R4: ELECTRICIDAD | V4: TELECOMUNICACIONES | Z4: GAS | AD4: URBANIZACIÓN | AH4: CONTROL/GESTIÓN
A6: Nº | B6: CATEGORÍA | C6: ACTIVIDAD | D6: INI | E6: DUR | F6: 1 | G6: 2 | H6: 3 | I6: 4 | J6: 5 | K6: 6 | L6: 7 | M6: 8 | N6: 9 | O6: 10 | P6: 11 | Q6: 12 | R6: 13 | S6: 14 | T6: 15 | U6: 16 | V6: 17 | W6: 18 | X6: 19 | Y6: 20 | Z6: 21 | AA6: 22 | AB6: 23 | AC6: 24 | AD6: 25 | AE6: 26 | AF6: 27 | AG6: 28 | AH6: 29 | AI6: 30 | AJ6: 31 | AK6: 32 | AL6: 33 | AM6: 34 | AN6: 35 | AO6: 36
A7: OBRA CIVIL
A8: 1 | B8: OBRA CIVIL | C8: ='PLAN DE OBRA'!C7 | D8: ='PLAN DE OBRA'!D7 | E8: ='PLAN DE OBRA'!E7
A9: 2 | B9: OBRA CIVIL | C9: ='PLAN DE OBRA'!C8 | D9: ='PLAN DE OBRA'!D8 | E9: ='PLAN DE OBRA'!E8
A10: 3 | B10: OBRA CIVIL | C10: ='PLAN DE OBRA'!C9 | D10: ='PLAN DE OBRA'!D9 | E10: ='PLAN DE OBRA'!E9
A11: 4 | B11: OBRA CIVIL | C11: ='PLAN DE OBRA'!C10 | D11: ='PLAN DE OBRA'!D10 | E11: ='PLAN DE OBRA'!E10
A12: SANEAMIENTO
A13: 5 | B13: SANEAMIENTO | C13: ='PLAN DE OBRA'!C12 | D13: ='PLAN DE OBRA'!D12 | E13: ='PLAN DE OBRA'!E12
A14: 6 | B14: SANEAMIENTO | C14: ='PLAN DE OBRA'!C13 | D14: ='PLAN DE OBRA'!D13 | E14: ='PLAN DE OBRA'!E13
A15: ABASTECIMIENTO
A16: 7 | B16: ABASTECIMIENTO | C16: ='PLAN DE OBRA'!C15 | D16: ='PLAN DE OBRA'!D15 | E16: ='PLAN DE OBRA'!E15
A17: ELECTRICIDAD
A18: 8 | B18: ELECTRICIDAD | C18: ='PLAN DE OBRA'!C17 | D18: ='PLAN DE OBRA'!D17 | E18: ='PLAN DE OBRA'!E17
A19: 9 | B19: ELECTRICIDAD | C19: ='PLAN DE OBRA'!C18 | D19: ='PLAN DE OBRA'!D18 | E19: ='PLAN DE OBRA'!E18
A20: 10 | B20: ELECTRICIDAD | C20: ='PLAN DE OBRA'!C19 | D20: ='PLAN DE OBRA'!D19 | E20: ='PLAN DE OBRA'!E19
A21: TELECOMUNICACIONES
A22: 11 | B22: TELECOMUNICACIONES | C22: ='PLAN DE OBRA'!C21 | D22: ='PLAN DE OBRA'!D21 | E22: ='PLAN DE OBRA'!E21
A23: GAS
A24: 12 | B24: GAS | C24: ='PLAN DE OBRA'!C23 | D24: ='PLAN DE OBRA'!D23 | E24: ='PLAN DE OBRA'!E23
A25: URBANIZACIÓN
A26: 13 | B26: URBANIZACIÓN | C26: ='PLAN DE OBRA'!C25 | D26: ='PLAN DE OBRA'!D25 | E26: ='PLAN DE OBRA'!E25
A27: 14 | B27: URBANIZACIÓN | C27: ='PLAN DE OBRA'!C26 | D27: ='PLAN DE OBRA'!D26 | E27: ='PLAN DE OBRA'!E26
A28: 15 | B28: URBANIZACIÓN | C28: ='PLAN DE OBRA'!C27 | D28: ='PLAN DE OBRA'!D27 | E28: ='PLAN DE OBRA'!E27
A29: 16 | B29: URBANIZACIÓN | C29: ='PLAN DE OBRA'!C28 | D29: ='PLAN DE OBRA'!D28 | E29: ='PLAN DE OBRA'!E28
A30: 17 | B30: URBANIZACIÓN | C30: ='PLAN DE OBRA'!C29 | D30: ='PLAN DE OBRA'!D29 | E30: ='PLAN DE OBRA'!E29
A31: CONTROL/GESTIÓN
A32: 18 | B32: CONTROL/GESTIÓN | C32: ='PLAN DE OBRA'!C31 | D32: ='PLAN DE OBRA'!D31 | E32: ='PLAN DE OBRA'!E31
A33: 19 | B33: CONTROL/GESTIÓN | C33: ='PLAN DE OBRA'!C32 | D33: ='PLAN DE OBRA'!D32 | E33: ='PLAN DE OBRA'!E32

Sheet CERTIFICACIONES
A1: DISTRIBUCIÓN DE INVERSIÓN MENSUAL — CERTIFICACIONES PREVISTAS
A2: ✔ Completado 10/04/2026. Distribución basada en Gantt (Plan de Obra) y BC3 (535.2.bc3). PEM = 3.737.657,65 €. NOTA: Electricidad, Telecomunicaciones y Gas no figuran en el BC3 civil → inversión = 0.
A4: ESTRUCTURA PREVISTA (a rellenar con presupuesto)
B5: CAPÍTULO / CATEGORÍA | C5: M1 | D5: M2 | E5: M3 | F5: M4 | G5: M5 | H5: M6 | I5: M7 | J5: M8 | K5: M9 | L5: M10 | M5: M11 | N5: M12 | O5: M13 | P5: M14 | Q5: M15 | R5: M16 | S5: M17 | T5: M18 | U5: M19 | V5: M20 | W5: M21 | X5: M22 | Y5: M23 | Z5: M24 | AA5: M25 | AB5: M26 | AC5: M27 | AD5: M28 | AE5: M29 | AF5: M30 | AG5: M31 | AH5: M32 | AI5: M33 | AJ5: M34 | AK5: M35 | AL5: M36
B6: OBRA CIVIL | C6: 73273.06 | D6: 73273.06 | E6: 56209.64 | F6: 56209.64 | G6: 56209.64 | H6: 56209.64 | I6: 56209.64 | J6: 56209.64 | K6: 307642.53 | L6: 307642.53 | M6: 307642.53 | N6: 307642.53 | O6: 307642.53 | P6: 307642.53 | Q6: 307642.53 | R6: 0 | S6: 0 | T6: 0
B7: SANEAMIENTO | C7: 0 | D7: 0 | E7: 0 | F7: 53661.4 | G7: 53661.4 | H7: 66862.21 | I7: 66862.21 | J7: 66862.21 | K7: 66862.21 | L7: 66862.21 | M7: 66862.21 | N7: 13200.81 | O7: 0 | P7: 0 | Q7: 0 | R7: 0 | S7: 0 | T7: 0
B8: ABASTECIMIENTO | C8: 0 | D8: 0 | E8: 0 | F8: 0 | G8: 0 | H8: 0 | I8: 0 | J8: 0 | K8: 0 | L8: 34729.39 | M8: 34729.39 | N8: 34729.39 | O8: 34729.39 | P8: 34729.39 | Q8: 0 | R8: 0 | S8: 0 | T8: 0
B9: ELECTRICIDAD | C9: 0 | D9: 0 | E9: 0 | F9: 0 | G9: 0 | H9: 0 | I9: 0 | J9: 0 | K9: 0 | L9: 0 | M9: 0 | N9: 0 | O9: 0 | P9: 0 | Q9: 0 | R9: 0 | S9: 0 | T9: 0
B10: TELECOMUNICACIONES | C10: 0 | D10: 0 | E10: 0 | F10: 0 | G10: 0 | H10: 0 | I10: 0 | J10: 0 | K10: 0 | L10: 0 | M10: 0 | N10: 0 | O10: 0 | P10: 0 | Q10: 0 | R10: 0 | S10: 0 | T10: 0
B11: GAS | C11: 0 | D11: 0 | E11: 0 | F11: 0 | G11: 0 | H11: 0 | I11: 0 | J11: 0 | K11: 0 | L11: 0 | M11: 0 | N11: 0 | O11: 0 | P11: 0 | Q11: 0 | R11: 0 | S11: 0 | T11: 0
B12: URBANIZACIÓN | C12: 0 | D12: 0 | E12: 0 | F12: 0 | G12: 0 | H12: 0 | I12: 0 | J12: 0 | K12: 0 | L12: 0 | M12: 0 | N12: 33746.81 | O12: 42361.43 | P12: 42361.43 | Q12: 72710.37 | R12: 40448.46 | S12: 40448.46 | T12: 20038.73
B13: CONTROL/GESTIÓN | C13: 6272.03 | D13: 6272.03 | E13: 6272.03 | F13: 6272.03 | G13: 6272.03 | H13: 6272.03 | I13: 6272.03 | J13: 6272.03 | K13: 6272.03 | L13: 6272.03 | M13: 6272.03 | N13: 6272.03 | O13: 6272.03 | P13: 6272.03 | Q13: 6272.03 | R13: 6272.03 | S13: 6272.03 | T13: 6272.03
B14: PRESUPUESTO TOTAL (PEM BC3 = 3,737,657.65 €) | C14: 79545.09 | D14: 79545.09 | E14: 62481.67 | F14: 116143.07 | G14: 116143.07 | H14: 129343.87 | I14: 129343.87 | J14: 129343.87 | K14: 380776.76 | L14: 415506.15 | M14: 415506.15 | N14: 395591.56 | O14: 391005.38 | P14: 391005.38 | Q14: 386624.93 | R14: 46720.49 | S14: 46720.49 | T14: 26310.76
B15: INVERSIÓN ACUMULADA (€) | C15: 79545.09 | D15: 159090.18 | E15: 221571.85 | F15: 337714.92 | G15: 453857.99 | H15: 583201.86 | I15: 712545.73 | J15: 841889.6 | K15: 1222666.4 | L15: 1638172.5 | M15: 2053678.7 | N15: 2449270.2 | O15: 2840275.6 | P15: 3231281 | Q15: 3617905.9 | R15: 3664626.4 | S15: 3711346.9 | T15: 3737657.6
B16: % CERTIFICADO ACUM. | C16: 2.13 | D16: 4.26 | E16: 5.93 | F16: 9.04 | G16: 12.14 | H16: 15.6 | I16: 19.06 | J16: 22.52 | K16: 32.71 | L16: 43.83 | M16: 54.95 | N16: 65.53 | O16: 75.99 | P16: 86.45 | Q16: 96.8 | R16: 98.05 | S16: 99.3 | T16: 100
